{"classification":{"category":{"name":"Data","normalized_name":"data","subcategories":[{"name":"Data","normalized_name":"data"}]}},"foundation":"NeoNephos Foundation","items":[{"category":"Data","id":"data--data--open-resource-discovery","name":"Open Resource Discovery","logo":"logos/21650be199994f364bbf202c65ec19f21d5ac321b38efd46115bc6672fbc6454.svg","subcategory":"Data","website":"https://open-resource-discovery.github.io/specification/","description":"ORD is an open protocol for the decentralized publishing and discovery of application and service metadata. It provides a structured schema for metadata such as endpoints, capabilities, documentation links, and ownership details, ensuring that application resources like APIs, events, data products and AI agents can be discovered, understood, and integrated consistently across different systems and marketplaces.\n","primary_repository_url":"https://github.com/open-resource-discovery"}]}